boids/__init__.py
boids/boid.py
boids/functions.py
boids/simulation.py
boids-0.2.1.dist-info/LICENSE
boids-0.2.1.dist-info/WHEEL
boids-0.2.1.dist-info/METADATA
boids-0.2.1.dist-info/RECORD
