Metadata-Version: 2.1
Name: boids
Version: 0.2.1
Summary: Example python package for boids simulation
Author-email: Gregor Decristoforo <gregor.decristoforo@gmail.com>
Classifier: License :: OSI Approved :: MIT License
Requires-Dist: pygame
Requires-Dist: numpy
Requires-Dist: pytest
Project-URL: Home, https://github.com/nordic-rse/boids
